{
  "$schema": "https://mintlify.com/docs.json",
  "name": "git-filter-repo",
  "theme": "aspen",
  "colors": {
    "primary": "#fa4c2a",
    "light": "#443b33",
    "dark": "#fa4c2a"
  },
  "favicon": "https://media.brand.dev/640d8e38-cc02-4dbe-8943-3a145e37f9ef.png",
  "logo": {
    "light": "https://media.brand.dev/36949707-debc-4882-9753-131bf18d268a.png",
    "dark": "https://media.brand.dev/36949707-debc-4882-9753-131bf18d268a.png"
  },
  "navbar": {
    "primary": {
      "type": "github",
      "href": "https://github.com/newren/git-filter-repo"
    }
  },
  "footer": {
    "socials": {
      "github": "https://github.com/newren/git-filter-repo"
    }
  },
  "navigation": {
    "tabs": [
      {
        "tab": "Documentation",
        "groups": [
          {
            "group": "Getting Started",
            "pages": [
              "introduction",
              "installation",
              "quickstart"
            ]
          },
          {
            "group": "Core Concepts",
            "pages": [
              "concepts/how-it-works",
              "concepts/design-rationale",
              "concepts/fresh-clone"
            ]
          },
          {
            "group": "Common Use Cases",
            "pages": [
              "use-cases/extracting-subdirectory",
              "use-cases/removing-sensitive-data",
              "use-cases/path-renaming",
              "use-cases/analyzing-repository"
            ]
          },
          {
            "group": "Guides",
            "pages": [
              "guides/basic-filtering",
              "guides/advanced-filtering",
              "guides/path-based-filtering",
              "guides/content-based-filtering",
              "guides/commit-message-rewriting",
              "guides/library-usage"
            ]
          },
          {
            "group": "Migration Guides",
            "pages": [
              "migration/from-filter-branch",
              "migration/from-bfg"
            ]
          },
          {
            "group": "Examples",
            "pages": [
              "examples/cheat-sheet",
              "examples/user-scenarios",
              "examples/demo-scripts"
            ]
          },
          {
            "group": "Resources",
            "pages": [
              "resources/faq",
              "resources/troubleshooting",
              "resources/contributing"
            ]
          }
        ]
      },
      {
        "tab": "API Reference",
        "groups": [
          {
            "group": "Command Line",
            "pages": [
              "api/cli-overview",
              "api/path-options",
              "api/content-options",
              "api/rename-options",
              "api/commit-options",
              "api/ref-options",
              "api/output-options"
            ]
          },
          {
            "group": "Python Library",
            "pages": [
              "api/python-overview",
              "api/python-data-structures",
              "api/python-filtering",
              "api/python-callbacks"
            ]
          }
        ]
      }
    ]
  }
}
